<?xml version="1.0" encoding="UTF-8"?>
<configuration scan="true" scanPeriod="60 seconds">

    <statusListener class="ch.qos.logback.core.status.OnConsoleStatusListener"/>

    <!-- ================= 공통 패턴 ================= -->
    <property name="LOG_PATTERN"
              value="%d{yyyy-MM-dd HH:mm:ss.SSS} %5level [%thread] %logger - [%X{traceId:-NONE}] %msg%n"/>

    <!-- ========================================================= -->
    <!-- ======================== LOCAL =========================== -->
    <!-- ========================================================= -->
    <springProfile name="local">

        <include resource="org/springframework/boot/logging/logback/defaults.xml"/>

        <appender name="CONSOLE" class="ch.qos.logback.core.ConsoleAppender">
            <encoder>
                <pattern>${LOG_PATTERN}</pattern>
            </encoder>
        </appender>

        <appender name="FILE" class="ch.qos.logback.core.rolling.RollingFileAppender">
            <file>log/server.log</file>
            <encoder>
                <pattern>${LOG_PATTERN}</pattern>
            </encoder>
            <rollingPolicy class="ch.qos.logback.core.rolling.TimeBasedRollingPolicy">
                <fileNamePattern>log/server.%d{yyyy-MM-dd}.log</fileNamePattern>
                <maxHistory>30</maxHistory>
                <totalSizeCap>20GB</totalSizeCap>
            </rollingPolicy>
        </appender>

        <root level="INFO">
            <appender-ref ref="CONSOLE"/>
            <appender-ref ref="FILE"/>
        </root>

    </springProfile>

    <!-- ========================================================= -->
    <!-- ========================= PROD =========================== -->
    <!-- ========================================================= -->
    <springProfile name="prod">

        <property name="LOG_PATH" value="log"/>
        <property name="LOG_FILE_NAME" value="server"/>
        <property name="LOG_PATTERN"
                  value="%d{yyyy-MM-dd HH:mm:ss.SSS} %5level [%thread] %logger - [%X{traceId:-NONE}] %msg%n"/>

        <!-- 콘솔은 동기로 root에 직접 -->
        <appender name="CONSOLE" class="ch.qos.logback.core.ConsoleAppender">
            <encoder>
                <pattern>${LOG_PATTERN}</pattern>
            </encoder>
        </appender>

        <!-- 파일 -->
        <appender name="FILE" class="ch.qos.logback.core.rolling.RollingFileAppender">
            <file>${LOG_PATH}/${LOG_FILE_NAME}.log</file>
            <encoder>
                <pattern>${LOG_PATTERN}</pattern>
            </encoder>
            <rollingPolicy class="ch.qos.logback.core.rolling.TimeBasedRollingPolicy">
                <fileNamePattern>${LOG_PATH}/%d{yyyy-MM, aux}/${LOG_FILE_NAME}.%d{yyyy-MM-dd}.log</fileNamePattern>
                <maxHistory>30</maxHistory>
                <totalSizeCap>20GB</totalSizeCap>
            </rollingPolicy>
        </appender>

        <!-- 파일만 비동기 -->
        <appender name="ASYNC_FILE" class="ch.qos.logback.classic.AsyncAppender">
            <queueSize>8192</queueSize>
            <discardingThreshold>0</discardingThreshold>
            <neverBlock>true</neverBlock>
            <maxFlushTime>1000</maxFlushTime>
            <appender-ref ref="FILE"/>
        </appender>

        <root level="INFO">
            <appender-ref ref="CONSOLE"/>
            <appender-ref ref="ASYNC_FILE"/>
        </root>

    </springProfile>

</configuration>